pymodaq_plugins_avantes/__init__.py
pymodaq_plugins_avantes/utils.py
pymodaq_plugins_avantes/app/__init__.py
pymodaq_plugins_avantes/daq_move_plugins/__init__.py
pymodaq_plugins_avantes/daq_viewer_plugins/__init__.py
pymodaq_plugins_avantes/daq_viewer_plugins/plugins_0D/__init__.py
pymodaq_plugins_avantes/daq_viewer_plugins/plugins_1D/__init__.py
pymodaq_plugins_avantes/daq_viewer_plugins/plugins_1D/daq_1Dviewer_Avantes.py
pymodaq_plugins_avantes/daq_viewer_plugins/plugins_2D/__init__.py
pymodaq_plugins_avantes/daq_viewer_plugins/plugins_ND/__init__.py
pymodaq_plugins_avantes/exporters/__init__.py
pymodaq_plugins_avantes/extensions/__init__.py
pymodaq_plugins_avantes/hardware/AvaSpec_ULS2048CL_EVO_Controller.py
pymodaq_plugins_avantes/hardware/__init__.py
pymodaq_plugins_avantes/hardware/avaspec.py
pymodaq_plugins_avantes/models/__init__.py
pymodaq_plugins_avantes/resources/__init__.py
pymodaq_plugins_avantes/resources/config_template.toml
pymodaq_plugins_avantes/scanners/__init__.py
pymodaq_plugins_avantes-5.0.0.dist-info/METADATA
pymodaq_plugins_avantes-5.0.0.dist-info/WHEEL
pymodaq_plugins_avantes-5.0.0.dist-info/entry_points.txt
pymodaq_plugins_avantes-5.0.0.dist-info/licenses/LICENSE
pymodaq_plugins_avantes-5.0.0.dist-info/RECORD
