Metadata-Version: 2.4
Name: pymodaq_plugins_avantes
Version: 5.0.0
Summary: Plugin for spectrometers from Avantes
Project-URL: Homepage, https://pymodaq.cnrs.fr
Project-URL: Documentation , https://pymodaq.cnrs.fr
Project-URL: Repository , https://github.com/PyMoDAQ/pymodaq_plugins_avantes
Author-email: Bernhard Lang <bernhard.lang@unige.ch>, Eric Studemann Lang <eric.studemann@unige.ch>
Maintainer-email: Bernhard Lang <bernhard.lang@unige.ch>
License: The MIT License (MIT)
License-File: LICENSE
Classifier: Development Status :: 5 - Production/Stable
Classifier: Intended Audience :: Science/Research
Classifier: License :: OSI Approved :: MIT License
Classifier: Natural Language :: English
Classifier: Operating System :: OS Independent
Classifier: Programming Language :: Python :: 3.8
Classifier: Programming Language :: Python :: 3.9
Classifier: Programming Language :: Python :: 3.10
Classifier: Programming Language :: Python :: 3.11
Classifier: Topic :: Scientific/Engineering :: Human Machine Interfaces
Classifier: Topic :: Scientific/Engineering :: Visualization
Classifier: Topic :: Software Development :: Libraries :: Python Modules
Classifier: Topic :: Software Development :: User Interfaces
Requires-Python: >=3.8
Requires-Dist: pymodaq-data
Requires-Dist: pymodaq-utils
Requires-Dist: pymodaq>=5.0.0
